nicehash/__init__.py
nicehash/nicehash.py
nicehash-0.0.3.dist-info/METADATA
nicehash-0.0.3.dist-info/WHEEL
nicehash-0.0.3.dist-info/top_level.txt
nicehash-0.0.3.dist-info/RECORD
