Metadata-Version: 1.1
Name: nicehash
Version: 0.0.3
Summary: NiceHash Python API
Home-page: https://www.adgstudios.co.za
Author: Ashlin Darius Govindasamy
Author-email: adgrules@hotmail.com
License: MIT
Platform: UNKNOWN
Classifier: Programming Language :: Python :: 3
Classifier: License :: OSI Approved :: MIT License
Classifier: Operating System :: OS Independent
